duit/__init__.py
duit/annotation/Annotation.py
duit/annotation/AnnotationFinder.py
duit/annotation/AnnotationList.py
duit/annotation/__init__.py
duit/arguments/Argument.py
duit/arguments/Arguments.py
duit/arguments/__init__.py
duit/arguments/adapters/BaseTypeAdapter.py
duit/arguments/adapters/BooleanTypeAdapter.py
duit/arguments/adapters/DefaultTypeAdapter.py
duit/arguments/adapters/EnumTypeAdapter.py
duit/arguments/adapters/PathTypeAdapter.py
duit/arguments/adapters/VectorTypeAdapter.py
duit/arguments/adapters/__init__.py
duit/collections/Stack.py
duit/collections/__init__.py
duit/event/Event.py
duit/event/__init__.py
duit/iterator/AnnotationIterator.py
duit/iterator/DataFieldIterator.py
duit/iterator/ObjectIterator.py
duit/iterator/__init__.py
duit/model/AttributeIdentifier.py
duit/model/DataField.py
duit/model/DataFieldPlugin.py
duit/model/DataList.py
duit/model/SelectableDataList.py
duit/model/__init__.py
duit/settings/Setting.py
duit/settings/Settings.py
duit/settings/__init__.py
duit/settings/serialiser/BaseSerializer.py
duit/settings/serialiser/DefaultSerializer.py
duit/settings/serialiser/EnumSerializer.py
duit/settings/serialiser/NumpySerializer.py
duit/settings/serialiser/PathSerializer.py
duit/settings/serialiser/VectorSerializer.py
duit/settings/serialiser/__init__.py
duit/ui/BaseProperty.py
duit/ui/BasePropertyPanel.py
duit/ui/ContainerHelper.py
duit/ui/PropertyRegistry.py
duit/ui/__init__.py
duit/ui/annotations/ActionAnnotation.py
duit/ui/annotations/BooleanAnnotation.py
duit/ui/annotations/EnumAnnotation.py
duit/ui/annotations/ListAnnotation.py
duit/ui/annotations/NumberAnnotation.py
duit/ui/annotations/OptionsAnnotation.py
duit/ui/annotations/PathAnnotation.py
duit/ui/annotations/ProgressAnnotation.py
duit/ui/annotations/SliderAnnotation.py
duit/ui/annotations/TextAnnotation.py
duit/ui/annotations/TitleAnnoation.py
duit/ui/annotations/UIAnnotation.py
duit/ui/annotations/VectorAnnotation.py
duit/ui/annotations/__init__.py
duit-0.1.20.dist-info/LICENSE
duit-0.1.20.dist-info/METADATA
duit-0.1.20.dist-info/WHEEL
duit-0.1.20.dist-info/top_level.txt
duit-0.1.20.dist-info/RECORD
