Metadata-Version: 2.1
Name: duit
Version: 0.1.20
Summary: Duit is a toolkit to create simple user-interfaces for python.
Home-page: https://github.com/cansik/duit
Author: Florian Bruggisser
Author-email: github@broox.ch
License: MIT License
License-File: LICENSE
Requires-Dist: vector
Requires-Dist: pyperclip
Requires-Dist: numpy
Requires-Dist: appnope; platform_system == "Darwin"
Provides-Extra: all
Requires-Dist: open3d>=0.19.0; extra == "all"
Requires-Dist: tk~=0.1.0; extra == "all"
Requires-Dist: customtkinter~=5.2.2; extra == "all"
Requires-Dist: wxPython~=4.2.3.0; extra == "all"
Requires-Dist: nicegui~=2.22.2; extra == "all"
Provides-Extra: nicegui
Requires-Dist: nicegui~=2.22.2; extra == "nicegui"
Provides-Extra: open3d
Requires-Dist: open3d>=0.19.0; extra == "open3d"
Provides-Extra: tk
Requires-Dist: tk~=0.1.0; extra == "tk"
Requires-Dist: customtkinter~=5.2.2; extra == "tk"
Provides-Extra: wx
Requires-Dist: wxPython~=4.2.3.0; extra == "wx"
